ob_example/__init__.py
ob_example/_nbdev.py
ob_example/plotter/__init__.py
ob_example/plotter/picture_output.py
ob_example/utils/__init__.py
ob_example/utils/libutils.py
ob_example-0.0.3.dist-info/LICENSE
ob_example-0.0.3.dist-info/METADATA
ob_example-0.0.3.dist-info/WHEEL
ob_example-0.0.3.dist-info/entry_points.txt
ob_example-0.0.3.dist-info/top_level.txt
ob_example-0.0.3.dist-info/RECORD
