Metadata-Version: 2.1
Name: ob-example
Version: 0.0.3
Summary: An example project that shows how to use nbdev-org-babel
Home-page: https://github.com/methuselah-0/nbdev-org-babel-example/tree/master/
Author: David Larsson
Author-email: david.larsson@selfhosted.xyz
License: Apache Software License 2.0
Keywords: org-babel org emacs
Platform: UNKNOWN
Classifier: Development Status :: 3 - Alpha
Classifier: Intended Audience :: Developers
Classifier: License :: OSI Approved :: Apache Software License
Classifier: Natural Language :: English
Classifier: Programming Language :: Python :: 3.6
Classifier: Programming Language :: Python :: 3.7
Classifier: Programming Language :: Python :: 3.8
Requires-Python: >=3.6
Requires-Dist: scipy (>=1.4.1)
Requires-Dist: numpy (>=1.18.4)
Requires-Dist: matplotlib (>=3.2.1)
